jspaste/__init__.py
jspaste/__main__.py
jspaste/delete.py
jspaste/errors.py
jspaste/get.py
jspaste/publish.py
jspaste/temporal.py
jspaste/vares.py
jspaste.py-0.1.dist-info/LICENSE.TXT
jspaste.py-0.1.dist-info/METADATA
jspaste.py-0.1.dist-info/WHEEL
jspaste.py-0.1.dist-info/top_level.txt
jspaste.py-0.1.dist-info/RECORD
