Metadata-Version: 2.1
Name: jspaste.py
Version: 0.1
Summary: Api Wrapper Of Jspaste, https://jspaste.tnfangel.repl.co/
Home-page: https://github.com/pruebando/jspaste
Author: Pruebando
Author-email: UNKNOWN
License: MIT
Download-URL: https://github.com/pruebando/jspaste/archive/refs/tags/0.1.tar.gz
Keywords: Pastebin,Jspaste,Api Wrapper
Platform: UNKNOWN
Classifier: Development Status :: 3 - Alpha
Classifier: Intended Audience :: Developers
Classifier: Topic :: Software Development :: Build Tools
Classifier: License :: OSI Approved :: MIT License
Classifier: Programming Language :: Python :: 3
Classifier: Programming Language :: Python :: 3.4
Classifier: Programming Language :: Python :: 3.5
Classifier: Programming Language :: Python :: 3.6
Classifier: Programming Language :: Python :: 3.7
Classifier: Programming Language :: Python :: 3.8
Classifier: Programming Language :: Python :: 3.9
